omni_cli/.sparql.py.swo
omni_cli/__init__.py
omni_cli/annotator/__init__.py
omni_cli/annotator/plugin.py
omni_cli/benchmarks.py
omni_cli/cli.py
omni_cli/config.py
omni_cli/datasets.py
omni_cli/docker.py
omni_cli/epoch.py
omni_cli/graph.py
omni_cli/model.py
omni_cli/orchestrator.py
omni_cli/plot.py
omni_cli/project.py
omni_cli/resources.py
omni_cli/sparql.py
omni_cli/sync.py
omni_cli/workflow.py
omnibench_cli-1.0.3.dist-info/LICENSE
omnibench_cli-1.0.3.dist-info/METADATA
omnibench_cli-1.0.3.dist-info/WHEEL
omnibench_cli-1.0.3.dist-info/entry_points.txt
omnibench_cli-1.0.3.dist-info/RECORD
