Metadata-Version: 2.1
Name: omnibench-cli
Version: 1.0.3
Summary: 
Home-page: https://renkulab.io/gitlab/btraven/omni-cli/
Author: btraven
Author-email: btraven@sdf.org
Requires-Python: >=3.8.1,<3.12
Classifier: Development Status :: 3 - Alpha
Classifier: Intended Audience :: Developers
Classifier: Intended Audience :: Science/Research
Classifier: License :: OSI Approved :: Apache Software License
Classifier: Operating System :: OS Independent
Classifier: Programming Language :: Python
Classifier: Programming Language :: Python :: 3
Classifier: Programming Language :: Python :: 3.9
Classifier: Programming Language :: Python :: 3.10
Classifier: Programming Language :: Python :: 3.11
Classifier: Programming Language :: Python :: 3.8
Classifier: Topic :: Software Development :: Libraries :: Python Modules
Requires-Dist: calamus (>=0.4.2,<0.5.0)
Requires-Dist: click (>=8.1.3,<9.0.0)
Requires-Dist: omnibenchmark (>=0.0.43,<0.0.44)
Requires-Dist: pydantic (>=1.10.2,<2.0.0)
Requires-Dist: pyyaml (>=6.0,<7.0)
Requires-Dist: renku (>=2.3.2,<3.0.0)
Requires-Dist: requests (<2.28.2)
Requires-Dist: sparqlwrapper (>=2.0.0,<3.0.0)
Project-URL: Repository, https://renkulab.io/gitlab/btraven/omni-cli/
